thrift/TMultiplexedProcessor.py
thrift/TRecursive.py
thrift/TSCons.py
thrift/TSerialization.py
thrift/TTornado.py
thrift/Thrift.py
thrift/__init__.py
thrift/compat.py
thrift/__pycache__/TMultiplexedProcessor.cpython-310.opt-1.pyc
thrift/__pycache__/TRecursive.cpython-310.opt-1.pyc
thrift/__pycache__/TSCons.cpython-310.opt-1.pyc
thrift/__pycache__/TSerialization.cpython-310.opt-1.pyc
thrift/__pycache__/TTornado.cpython-310.opt-1.pyc
thrift/__pycache__/Thrift.cpython-310.opt-1.pyc
thrift/__pycache__/__init__.cpython-310.opt-1.pyc
thrift/__pycache__/compat.cpython-310.opt-1.pyc
thrift/protocol/TBase.py
thrift/protocol/TBinaryProtocol.py
thrift/protocol/TCompactProtocol.py
thrift/protocol/THeaderProtocol.py
thrift/protocol/TJSONProtocol.py
thrift/protocol/TMultiplexedProtocol.py
thrift/protocol/TProtocol.py
thrift/protocol/TProtocolDecorator.py
thrift/protocol/__init__.py
thrift/protocol/fastbinary.cp310-win_amd64.pyd
thrift/protocol/__pycache__/TBase.cpython-310.opt-1.pyc
thrift/protocol/__pycache__/TBinaryProtocol.cpython-310.opt-1.pyc
thrift/protocol/__pycache__/TCompactProtocol.cpython-310.opt-1.pyc
thrift/protocol/__pycache__/THeaderProtocol.cpython-310.opt-1.pyc
thrift/protocol/__pycache__/TJSONProtocol.cpython-310.opt-1.pyc
thrift/protocol/__pycache__/TMultiplexedProtocol.cpython-310.opt-1.pyc
thrift/protocol/__pycache__/TProtocol.cpython-310.opt-1.pyc
thrift/protocol/__pycache__/TProtocolDecorator.cpython-310.opt-1.pyc
thrift/protocol/__pycache__/__init__.cpython-310.opt-1.pyc
thrift/server/THttpServer.py
thrift/server/TNonblockingServer.py
thrift/server/TProcessPoolServer.py
thrift/server/TServer.py
thrift/server/__init__.py
thrift/server/__pycache__/THttpServer.cpython-310.opt-1.pyc
thrift/server/__pycache__/TNonblockingServer.cpython-310.opt-1.pyc
thrift/server/__pycache__/TProcessPoolServer.cpython-310.opt-1.pyc
thrift/server/__pycache__/TServer.cpython-310.opt-1.pyc
thrift/server/__pycache__/__init__.cpython-310.opt-1.pyc
dt_thrift-0.20.0.dist-info/METADATA
dt_thrift-0.20.0.dist-info/WHEEL
dt_thrift-0.20.0.dist-info/top_level.txt
dt_thrift-0.20.0.dist-info/RECORD
